{
    "order": 10,
    "icon": "🇰🇷",
    "name": "한국 ETF",
    "country_code": "kor",
    "slack_channel": "C09FAU2NHM2",
    "initial_date": "2025-10-01",
    "strategy": {
        "tuning": {
            "MA_PERIOD": 50,
            "PORTFOLIO_TOPN": 8,
            "REPLACE_SCORE_THRESHOLD": 1.0
        },
        "static": {
            "COOLDOWN_DAYS": 1,
            "MAX_PER_CATEGORY": 1,
            "MARKET_REGIME_RISK_OFF_EQUITY_RATIO": 90
        },
        "expected_cagr": 99.11
    },
    "benchmarks": [
        {
            "ticker": "379800",
            "name": "Kodex 미국S&P500"
        },
        {
            "ticker": "426030",
            "name": "TIMEFOLIO 미국나스닥100액티브"
        },
        {
            "ticker": "456600",
            "name": "TIMEFOLIO 글로벌AI인공지능액티브"
        }
    ],
    "schedule": {
        "recommendation_cron": "1,11,21,31,41,51 9-16 * * 1-5",
        "notify_cron": "1,31 9-16 * * 1-5"
    },
    "slack": {
        "channel": "C09FAU2NHM2"
    }
}
